<?xml version='1.0' encoding='utf-8'?>
<LegacyAlbum>
  <art/>
  <collections/>
  <countries/>
  <genres/>
  <originally_available_at>2003-01-01</originally_available_at>
  <posters/>
  <producers/>
  <reviews/>
  <tags/>
  <tracks>
    <item guid="local://1183" path="tracks/db03d5f0ac086b85c647ac1b259327a5a3d276d5">
      <lyrics/>
      <moods/>
      <tags/>
    </item>
    <item guid="local://1175" path="tracks/0c8850f5a781adef93013fafca20d9e8a6e9cfdf">
      <lyrics/>
      <moods/>
      <tags/>
    </item>
    <item guid="local://1170" path="tracks/4ed9c72254b663bec3ff7b683c47042dfc46f4de">
      <lyrics/>
      <moods/>
      <tags/>
    </item>
    <item guid="local://1171" path="tracks/5d6c3fce9486c926b3fdcc4f9c3c8a39129ded87">
      <lyrics/>
      <moods/>
      <tags/>
    </item>
    <item guid="local://1172" path="tracks/eb22327d789cd373648a1f9e278305b3c063a910">
      <lyrics/>
      <moods/>
      <tags/>
    </item>
    <item guid="local://1173" path="tracks/ab68f606014d556c2b758336b6f1b56c278a52f9">
      <lyrics/>
      <moods/>
      <tags/>
    </item>
    <item guid="local://1167" path="tracks/d76f702c12ce79d0dfe03306cd0a0b28874fc23b">
      <lyrics/>
      <moods/>
      <tags/>
    </item>
    <item guid="local://1166" path="tracks/6caf7d72d4588fc954422ee39dd8577693a7ca9b">
      <lyrics/>
      <moods/>
      <tags/>
    </item>
    <item guid="local://1176" path="tracks/73f94de30c05009e6fcecc72f24db345016fb3c6">
      <lyrics/>
      <moods/>
      <tags/>
    </item>
    <item guid="local://1177" path="tracks/8840b594f1c1bc497086ef8f0fb9f6290511af61">
      <lyrics/>
      <moods/>
      <tags/>
    </item>
    <item guid="local://1178" path="tracks/4bab34c4c3b7a2ac32c9d7520d953e0ec1aeeb34">
      <lyrics/>
      <moods/>
      <tags/>
    </item>
    <item guid="local://1179" path="tracks/f89f614a2d3f7162365b1141eda0958281982754">
      <lyrics/>
      <moods/>
      <tags/>
    </item>
    <item guid="local://1169" path="tracks/6e5156804e6bd3b4643f961b238caecc9a4e2ca3">
      <lyrics/>
      <moods/>
      <tags/>
    </item>
    <item guid="local://1168" path="tracks/3e6e3162394716a6a1d9baf140c6d0a4b47fee59">
      <lyrics/>
      <moods/>
      <tags/>
    </item>
    <item guid="local://1181" path="tracks/03f7445cebbb832d3e184da9120229123f0059d0">
      <lyrics/>
      <moods/>
      <tags/>
    </item>
    <item guid="local://1180" path="tracks/90f9588f9bb51257f0e68ac57cc61c4d33786f66">
      <lyrics/>
      <moods/>
      <tags/>
    </item>
    <item guid="local://1174" path="tracks/4232e851e83f957a8f3fa1d486b7ea72bfe01291">
      <lyrics/>
      <moods/>
      <tags/>
    </item>
    <item guid="local://1182" path="tracks/987432870e808644983d739bdadf310e8782a181">
      <lyrics/>
      <moods/>
      <tags/>
    </item>
  </tracks>
</LegacyAlbum>
